Products/mcdutils/__init__.py
Products/mcdutils/interfaces.py
Products/mcdutils/mapping.py
Products/mcdutils/proxy.py
Products/mcdutils/sessiondata.py
Products/mcdutils/zcache.py
Products/mcdutils/ftests/__init__.py
Products/mcdutils/ftests/functest.py
Products/mcdutils/ftests/test_proxy.py
Products/mcdutils/tests/__init__.py
Products/mcdutils/tests/helpers.py
Products/mcdutils/tests/test_mapping.py
Products/mcdutils/tests/test_proxy.py
Products/mcdutils/tests/test_sessiondata.py
Products/mcdutils/tests/test_zcache.py
Products/mcdutils/www/add_items.pt
Products/mcdutils/www/add_mcp.pt
Products/mcdutils/www/add_mcsdc.pt
Products/mcdutils/www/add_mczcm.pt
products_mcdutils-5.0.dist-info/licenses/LICENSE.txt
products_mcdutils-5.0.dist-info/METADATA
products_mcdutils-5.0.dist-info/WHEEL
products_mcdutils-5.0.dist-info/top_level.txt
products_mcdutils-5.0.dist-info/RECORD
