Metadata-Version: 2.4
Name: Products.mcdutils
Version: 5.0
Summary: A Zope product with memcached-backed ZCache and Zope session implementations.
Author-email: Tres Seaver and contributors <tseaver@palladion.com>
Maintainer-email: Jens Vagelpohl <jens@dataflake.org>
License-Expression: ZPL-2.1
Project-URL: Documentation, https://mcdutils.readthedocs.io
Project-URL: Issues, https://github.com/dataflake/Products.mcdutils/issues
Project-URL: Source, https://github.com/dataflake/Products.mcdutils
Project-URL: Changelog, https://mcdutils.readthedocs.io/en/latest/changes.html
Keywords: Zope,session,memcache,memcached
Classifier: Development Status :: 6 - Mature
Classifier: Environment :: Web Environment
Classifier: Framework :: Zope
Classifier: Framework :: Zope :: 5
Classifier: Intended Audience :: Developers
Classifier: Operating System :: OS Independent
Classifier: Programming Language :: Python
Classifier: Programming Language :: Python :: 3
Classifier: Programming Language :: Python :: 3 :: Only
Classifier: Programming Language :: Python :: 3.10
Classifier: Programming Language :: Python :: 3.11
Classifier: Programming Language :: Python :: 3.12
Classifier: Programming Language :: Python :: 3.13
Classifier: Programming Language :: Python :: 3.14
Classifier: Topic :: Internet :: WWW/HTTP :: Session
Requires-Python: >=3.10
License-File: LICENSE.txt
Requires-Dist: python-memcached
Requires-Dist: Zope>=5
Provides-Extra: docs
Requires-Dist: Sphinx; extra == "docs"
Requires-Dist: repoze.sphinx.autointerface; extra == "docs"
Requires-Dist: furo; extra == "docs"
Dynamic: license-file
